iabwrapper/__init__.py
iabwrapper/wrapper.py
IABwrapper-1.0.0.dist-info/METADATA
IABwrapper-1.0.0.dist-info/WHEEL
IABwrapper-1.0.0.dist-info/top_level.txt
IABwrapper-1.0.0.dist-info/RECORD
