Metadata-Version: 2.1
Name: IABwrapper
Version: 1.0.0
Summary: Wrapper around anjlab's Android In-app Billing Version 3 to be used in Kivy apps
Home-page: https://github.com/shashi278/android-iab-v3-kivy
Author: Shashi Ranjan
Author-email: shashiranjankv@gmail.com
License: UNKNOWN
Keywords: iab playstore billing android kivy-application kivy python
Platform: UNKNOWN
Classifier: Programming Language :: Python :: 3
Classifier: License :: OSI Approved :: MIT License
Classifier: Operating System :: Android
Requires-Python: >=3.6
Requires-Dist: kivy
